setup.py
PyScanner.egg-info/PKG-INFO
PyScanner.egg-info/SOURCES.txt
PyScanner.egg-info/dependency_links.txt
PyScanner.egg-info/top_level.txt
scanner/__init__.py
scanner/scanner.py