Metadata-Version: 1.0
Name: PyScanner
Version: 1.0.3
Summary: Java-like input scanner.
Home-page: https://github.com/Bekt/PyScanner
Author: Kanat Bekt
Author-email: bekt17@gmail.com
License: UNKNOWN
Platform: UNKNOWN
